graphs-0.0.3.dist-info/METADATA
graphs-0.0.3.dist-info/metadata.json
graphs-0.0.3.dist-info/DESCRIPTION.rst
graphs-0.0.3.dist-info/top_level.txt
graphs-0.0.3.dist-info/RECORD
graphs-0.0.3.dist-info/WHEEL
graphs/__init__.py
graphs/__init__.pyc
graphs/embed.py
graphs/reorder.py
graphs/analysis.py
graphs/mini_six.py
graphs/viz.py
graphs/construction/regularized.py
graphs/construction/geometric.py
graphs/construction/b_matching.py
graphs/construction/neighbors.py
graphs/construction/msg.py
graphs/construction/__init__.py
graphs/construction/incremental.py
graphs/construction/spanning_tree.py
graphs/construction/downsample.py
graphs/construction/rand.py
graphs/construction/directed.py
graphs/construction/tests/test_msg.py
graphs/construction/tests/test_directed.py
graphs/construction/tests/test_regularized.py
graphs/construction/tests/test_geometric.py
graphs/construction/tests/__init__.py
graphs/construction/tests/test_rand.py
graphs/construction/tests/test_neighbors.py
graphs/construction/tests/test_spanning_tree.py
graphs/construction/tests/test_downsample.py
graphs/construction/tests/test_b_matching.py
graphs/construction/tests/test_incremental.py
graphs/base/pairs.py
graphs/base/__init__.py
graphs/base/adj.py
graphs/base/base.py
graphs/base/tests/test_adj.py
graphs/base/tests/__init__.py
graphs/base/tests/test_static.py
graphs/base/tests/test_pairs.py
graphs/base/tests/test_base.py
graphs/generators/trajectories.py
graphs/generators/shapes.py
graphs/generators/__init__.py
graphs/generators/mountain_car.py
graphs/generators/swiss_roll.py
graphs/generators/tests/test_swiss_roll.py
graphs/generators/tests/test_mountain_car.py
graphs/generators/tests/__init__.py
graphs/generators/tests/test_shapes.py
graphs/generators/tests/test_trajectories.py
graphs/tests/__init__.py
graphs/tests/test_reorder.py
graphs/mixins/__init__.py
graphs/mixins/embed.py
graphs/mixins/_betweenness.py
graphs/mixins/analysis.py
graphs/mixins/label.py
graphs/mixins/viz.py
