Metadata-Version: 2.0
Name: graphs
Version: 0.0.3
Summary: All things graph.
Home-page: http://github.com/all-umass/graphs
Author: CJ Carey
Author-email: perimosocordiae@gmail.com
License: MIT
Platform: UNKNOWN
Requires-Dist: numpy (>=1.8)
Requires-Dist: scipy (>=0.14)
Requires-Dist: scikit-learn (>=0.15)
Requires-Dist: matplotlib (>=1.3.1)
